weberist/__init__.py
weberist/base/README.md
weberist/base/__init__.py
weberist/base/config.py
weberist/base/data.py
weberist/base/drivers.py
weberist/base/exceptions.py
weberist/base/managers.py
weberist/base/stealth/__init__.py
weberist/base/stealth/js/error.stack.override.js
weberist/base/stealth/js/selenium.fingerprint.js
weberist/base/stealth/js/webgl.worker.override.js
weberist/base/stealth/tools.py
weberist/core/__init__.py
weberist/core/drivers.py
weberist/docker/Dockerfile
weberist/docker/Dockerfile-chrome
weberist/docker/browsers
weberist/docker/chrome-entrypoint.sh
weberist/docker/docker-compose-selenoid.yml
weberist/docker/firefox-entrypoint.sh
weberist/generic/__init__.py
weberist/generic/constants.py
weberist/generic/shortcuts.py
weberist/generic/types.py
weberist/generic/utils.py
weberist/utils/__init__.py
weberist/utils/docker.py
weberist/utils/helpers.py
weberist/utils/javascript.py
weberist-0.3.1.dist-info/METADATA
weberist-0.3.1.dist-info/WHEEL
weberist-0.3.1.dist-info/RECORD
