Metadata-Version: 2.1
Name: weberist
Version: 0.3.1
Summary: Adapter for Selenium
License: MIT
Author: bessavagner
Author-email: bessavagner@gmail.com
Requires-Python: >=3.12,<4.0
Classifier: License :: OSI Approved :: MIT License
Classifier: Programming Language :: Python :: 3
Classifier: Programming Language :: Python :: 3.12
Requires-Dist: beautifulsoup4 (>=4.12.3,<5.0.0)
Requires-Dist: docker (>=7.1.0,<8.0.0)
Requires-Dist: lxml (>=5.3.0,<6.0.0)
Requires-Dist: nest-asyncio (>=1.6.0,<2.0.0)
Requires-Dist: selenium (>=4.23.1,<5.0.0)
Requires-Dist: selenium-stealth (>=1.0.6,<2.0.0)
Requires-Dist: webdriver-manager (>=4.0.2,<5.0.0)
